EChO/__init__.py
EChO/__main__.py
EChO/bot/__init__.py
EChO/bot/check.py
EChO/server/__init__.py
EChO/server/xshell.py
EChO_Framework-1.2.dist-info/LICENSE
EChO_Framework-1.2.dist-info/METADATA
EChO_Framework-1.2.dist-info/WHEEL
EChO_Framework-1.2.dist-info/top_level.txt
EChO_Framework-1.2.dist-info/RECORD
