Metadata-Version: 2.1
Name: EChO-Framework
Version: 1.2
Summary: EChO Framework
Home-page: https://github.com/A2577467404/EChO-Framework
Author: MixacPROD
Author-email: mixacprod@idlestudios.top
License: UNKNOWN
Project-URL: Bug Tracker, https://github.com/A2577467404/EChO-Framework/issues
Platform: UNKNOWN
Classifier: Programming Language :: Python :: 3
Classifier: Operating System :: OS Independent
Requires-Python: >=3.8
License-File: LICENSE
